{
    "schema":{
        "fields":[
            {
                "name":"index",
                "type":"integer"
            },
            {
                "name":"external_variable_input",
                "type":"string"
            },
            {
                "name":"scenario",
                "type":"string"
            },
            {
                "name":"value",
                "type":"number"
            }
        ],
        "primaryKey":[
            "index"
        ],
        "pandas_version":"1.4.0"
    },
    "data":[
        {
            "index":0,
            "external_variable_input":"CapexCoveredBySponsoring",
            "scenario":"Base case",
            "value":0.75
        },
        {
            "index":1,
            "external_variable_input":"CapexCoveredBySponsoring",
            "scenario":"Optimistic",
            "value":1.0
        },
        {
            "index":2,
            "external_variable_input":"CapexCoveredBySponsoring",
            "scenario":"Pessimistic",
            "value":0.6
        },
        {
            "index":3,
            "external_variable_input":"ElevatorRestaurantRevenues",
            "scenario":"Base case",
            "value":0.2
        },
        {
            "index":4,
            "external_variable_input":"ElevatorRestaurantRevenues",
            "scenario":"Optimistic",
            "value":0.6
        },
        {
            "index":5,
            "external_variable_input":"ElevatorRestaurantRevenues",
            "scenario":"Pessimistic",
            "value":0.0
        },
        {
            "index":6,
            "external_variable_input":"IncreaseAnnualVisitorsCustomerSatisfaction",
            "scenario":"Base case",
            "value":150.0
        },
        {
            "index":7,
            "external_variable_input":"IncreaseAnnualVisitorsCustomerSatisfaction",
            "scenario":"Optimistic",
            "value":500.0
        },
        {
            "index":8,
            "external_variable_input":"IncreaseAnnualVisitorsCustomerSatisfaction",
            "scenario":"Pessimistic",
            "value":125.0
        },
        {
            "index":9,
            "external_variable_input":"IncreaseAnnualVisitorsLandmarkValue",
            "scenario":"Base case",
            "value":250.0
        },
        {
            "index":10,
            "external_variable_input":"IncreaseAnnualVisitorsLandmarkValue",
            "scenario":"Optimistic",
            "value":400.0
        },
        {
            "index":11,
            "external_variable_input":"IncreaseAnnualVisitorsLandmarkValue",
            "scenario":"Pessimistic",
            "value":100.0
        },
        {
            "index":12,
            "external_variable_input":"PricePerKwH",
            "scenario":"Base case",
            "value":0.06
        },
        {
            "index":13,
            "external_variable_input":"PricePerKwH",
            "scenario":"Optimistic",
            "value":0.07
        },
        {
            "index":14,
            "external_variable_input":"PricePerKwH",
            "scenario":"Pessimistic",
            "value":0.05
        }
    ]
}