{
    "schema":{
        "fields":[
            {
                "name":"index",
                "type":"integer"
            },
            {
                "name":"key_output",
                "type":"string"
            },
            {
                "name":"theme",
                "type":"string"
            },
            {
                "name":"monetary",
                "type":"integer"
            },
            {
                "name":"smaller_the_better",
                "type":"integer"
            },
            {
                "name":"linear",
                "type":"integer"
            },
            {
                "name":"automatic",
                "type":"integer"
            },
            {
                "name":"start",
                "type":"number"
            },
            {
                "name":"end",
                "type":"number"
            }
        ],
        "primaryKey":[
            "index"
        ],
        "pandas_version":"1.4.0"
    },
    "data":[
        {
            "index":0,
            "key_output":"CAPEX",
            "theme":"Profit",
            "monetary":0,
            "smaller_the_better":1,
            "linear":0,
            "automatic":1,
            "start":null,
            "end":null
        },
        {
            "index":1,
            "key_output":"Energy cost",
            "theme":"Profit",
            "monetary":0,
            "smaller_the_better":1,
            "linear":1,
            "automatic":1,
            "start":null,
            "end":null
        },
        {
            "index":2,
            "key_output":"RE %",
            "theme":"Planet",
            "monetary":0,
            "smaller_the_better":0,
            "linear":0,
            "automatic":1,
            "start":null,
            "end":null
        },
        {
            "index":3,
            "key_output":"Carbon footprint reduction",
            "theme":"Planet",
            "monetary":0,
            "smaller_the_better":0,
            "linear":0,
            "automatic":1,
            "start":null,
            "end":null
        },
        {
            "index":4,
            "key_output":"Actual carbon emission",
            "theme":"Planet",
            "monetary":0,
            "smaller_the_better":1,
            "linear":0,
            "automatic":1,
            "start":null,
            "end":null
        },
        {
            "index":5,
            "key_output":"Increase in employee engagement score",
            "theme":"People",
            "monetary":0,
            "smaller_the_better":0,
            "linear":0,
            "automatic":1,
            "start":null,
            "end":null
        },
        {
            "index":6,
            "key_output":"Increase in employee recommendation rate",
            "theme":"People",
            "monetary":0,
            "smaller_the_better":0,
            "linear":0,
            "automatic":1,
            "start":null,
            "end":null
        },
        {
            "index":7,
            "key_output":"Increase in Net Promotor Score",
            "theme":"People",
            "monetary":0,
            "smaller_the_better":0,
            "linear":0,
            "automatic":1,
            "start":null,
            "end":null
        },
        {
            "index":8,
            "key_output":"Increase in brand value",
            "theme":"People",
            "monetary":0,
            "smaller_the_better":0,
            "linear":0,
            "automatic":1,
            "start":null,
            "end":null
        }
    ]
}