{
    "schema":{
        "fields":[
            {
                "name":"index",
                "type":"integer"
            },
            {
                "name":"case_text_element",
                "type":"string"
            },
            {
                "name":"value",
                "type":"string"
            }
        ],
        "primaryKey":[
            "index"
        ],
        "pandas_version":"1.4.0"
    },
    "data":[
        {
            "index":0,
            "case_text_element":"title_front_page",
            "value":"Report of the performed Refugee case"
        },
        {
            "index":1,
            "case_text_element":"strategic_challenge",
            "value":"How to balance scarce resources among refugees in their region"
        }
    ]
}